src/server.py
codemie_mcp_datasources-0.1.322.dist-info/METADATA
codemie_mcp_datasources-0.1.322.dist-info/WHEEL
codemie_mcp_datasources-0.1.322.dist-info/entry_points.txt
codemie_mcp_datasources-0.1.322.dist-info/RECORD
