Metadata-Version: 2.1
Name: codemie-mcp-datasources
Version: 0.1.322
Summary: MCP server for connecting to CodeMie Datasources
Author: Nikita Levyankov
Author-email: nikita_levyankov@epam.com
Requires-Python: >=3.12,<4.0
Classifier: Programming Language :: Python :: 3
Classifier: Programming Language :: Python :: 3.12
Requires-Dist: certifi (>=2025.1.31,<2026.0.0)
Requires-Dist: codemie-sdk-python (==0.1.322)
Requires-Dist: httpx (>=0.27.0,<0.28.0)
Requires-Dist: mcp (>=1.6.0,<2.0.0)
